<?xml version="1.0" ?>
<PyBrain>
	<Network class="pybrain.structure.networks.feedforward.FeedForwardNetwork" name="FeedForwardNetwork-15">
		<name val="u'FeedForwardNetwork-15'"/>
		<Modules>
			<LinearLayer class="pybrain.structure.modules.linearlayer.LinearLayer" inmodule="True" name="LinearLayer-7">
				<dim val="300"/>
			</LinearLayer>
			<SoftmaxLayer class="pybrain.structure.modules.softmax.SoftmaxLayer" name="SoftmaxLayer-16" outmodule="True">
				<dim val="3"/>
			</SoftmaxLayer>
			<SigmoidLayer class="pybrain.structure.modules.sigmoidlayer.SigmoidLayer" name="SigmoidLayer-8">
				<dim val="10"/>
			</SigmoidLayer>
			<SigmoidLayer class="pybrain.structure.modules.sigmoidlayer.SigmoidLayer" name="SigmoidLayer-17">
				<dim val="10"/>
			</SigmoidLayer>
			<SigmoidLayer class="pybrain.structure.modules.sigmoidlayer.SigmoidLayer" name="SigmoidLayer-18">
				<dim val="10"/>
			</SigmoidLayer>
			<SigmoidLayer class="pybrain.structure.modules.sigmoidlayer.SigmoidLayer" name="SigmoidLayer-19">
				<dim val="10"/>
			</SigmoidLayer>
			<SigmoidLayer class="pybrain.structure.modules.sigmoidlayer.SigmoidLayer" name="SigmoidLayer-20">
				<dim val="10"/>
			</SigmoidLayer>
		</Modules>
		<Connections>
			<FullConnection class="pybrain.structure.connections.full.FullConnection" name="FullConnection-10">
				<inmod val="LinearLayer-7"/>
				<outmod val="SigmoidLayer-19"/>
				<Parameters>[-1.1374157689312865, 1.0413799235412333, 0.20641279924970554, 1.0075941340167072, 1.835478932701138, 0.4194751773762404, 1.770894296267294, -1.0222152077857534, 0.13245240092304569, -0.41902589705020254, 0.40411129823568892, -0.36281745064569493, -1.4683238934582759, 0.27787817632024059, 0.3036373809348874, 1.8459554711322161, 0.55590341244507113, -0.61202124997649643, 1.2564362119281594, 0.30386023979604954, 0.20983504541383696, 0.91138895045703727, 0.95601722140753409, 1.6508383717726709, 1.1676328281280179, -0.4990240281821926, 1.1873625016984446, -0.47574702735352753, 0.63217996291854828, 1.219422929482963, -0.26768107319108697, 0.18114854536661906, -0.47245488846463946, -0.19103610831525927, -0.39871813166195524, -0.22359258693714501, 2.2501823260449139, -0.62148221104614454, -1.4681726818659426, -1.8047542203383813, 0.15212914847040876, 0.72384918695981715, 0.96654210217866288, -1.7500751547039961, -2.0983775888889897, -1.0052818053048973, 1.5357114695878151, -1.0455930112123926, 0.3167022136658178, -0.13115286366205881, -0.1842188164296133, 2.6015063990299367, -0.63101619688623689, -0.13488717214141718, 1.3142743992182557, 0.70741756979026371, -2.0746381675470298, 0.87490156684966314, 0.2290408795712113, 0.35737804064021178, -1.481321595227536, -1.847941360192831, -0.48481086038991622, -0.37392034916313877, -1.0180705715772853, -0.84206027901730218, -1.6692052754328734, -1.6161036884688456, -1.0270283152161914, -0.24117702791552059, 0.6986091821005902, -0.046741550128533309, 0.18769317758902546, 0.89194872259290992, 2.6375364193855235, -0.68870119117208761, 0.31079216125877035, -0.25119356616951927, -0.82029954859763865, 1.6853230264091696, 0.30615738732549924, -1.1872597256684565, 0.00097405345277631775, -0.30664934607512651, -1.0742082851590806, 0.61837226415308233, -0.95424503496446933, -0.43100989663168165, 1.1288004683832602, -0.65820479691165523, 1.3860396584667942, -2.5584657785490852, 0.66238727818061227, -1.6282862684412376, -1.1705223359103596, -0.26980834341641996, 2.0258283796995866, -0.60432820422024081, 0.70894550133845746, -0.30113056450095832, 1.0117629211164796, 1.547338604384302, -0.93264352110732274, 0.77236599801583505, 1.8596476975374572, -1.6705971602722902, 1.0385028658138353, -1.1925144965722085, -1.1590334083175025, 0.24749943804779226, -0.37781318508418327, -0.75699044487810641, -0.25094491281085718, -0.71477562511755566, -0.056278632920412575, 1.536525708432583, 0.74757404143299455, 1.278734936691277, -0.52606797173661479, -0.87021208907889003, -0.40276536004743041, 0.85075638919631003, 1.3188807422530051, 0.10724909016709003, -0.22991932870613552, -0.57319841319795728, -1.4842543170141722, -1.306608763659455, 0.92665296105963535, -0.81679981397278156, -0.60957157126064521, -0.93246170252251492, -0.31828690364457435, -1.2758951249354695, 0.1029921256382664, 0.52651733137129031, -1.6411925238994891, -0.67202781833643932, 1.1701205418547027, -0.65931175595586244, -1.7190525567910548, -0.78116815265183481, 0.79746801404676493, -0.51622089904760404, 0.064197626896442497, 2.1687426864002708, -0.26030316534011166, -1.0553613759450839, -1.8896961204187224, 2.0475719697971146, 2.3621178887525525, -1.8471303223857864, 2.5128552689768617, -0.085334597344296381, -0.44971650242849637, -1.7238333286866738, -0.41037484799895735, 0.19967981313616831, -0.14131255034076964, 1.4157417574838935, 0.28702446789407937, -1.1745637231544286, 0.098568368397394357, 0.69679505894634641, 1.4556326399033166, 1.4745078733629786, 0.90844626345810242, -0.35506045127803509, -0.13957977552720621, 1.5169057085295674, 0.11612364644018325, 0.56583050829396064, 1.6878303713431972, -1.3814410651116624, -0.60635294806016338, 0.080122005244018815, -0.23239071317371437, -0.74779076386532795, 0.66917640415036572, 0.8914085321609222, -1.2003461685300629, 0.67465597421839274, -1.2193182287283211, -0.36702033350803254, 0.3272046303101539, -0.3080726083705948, 0.94407427739951688, -0.80447538815780606, -0.1994443909084907, -1.3970563965069678, -0.14246036199514187, 0.040151622256819668, -0.94609231606415023, 0.18456561100995111, -0.13117325462277568, 1.1288730325289862, -0.11358089075225751, -0.053424827809646705, -0.14647985068934349, -0.80302137744353685, -0.0070415333528838281, -0.88184547067767638, 1.6759576593526646, 1.3037735850160852, 0.6079742289061244, 0.42081481381296032, 2.0951392693185276, 0.17615196720774381, 0.56993184068843783, -1.0686127521690989, -0.40813080801725243, 0.34936449567742561, -0.18725393985684866, -0.61969597015677569, -0.16611826943752173, -0.18667949679365281, -0.34268689956395415, -0.23194752482854117, 0.4892198874014973, 0.10251924374934242, -1.9114914730597974, 0.11682326277784991, -0.99711137574846631, -0.36660717715152857, 1.0891871440344278, -0.58204221162980763, -1.1976843130386199, 1.714325051382612, -1.6050145833189025, 1.4596223074658985, 0.77683124243231638, -1.1051810543227401, 0.043993511787788278, 0.76412438671880434, 0.74656977261752444, 0.47171970689785181, -1.1985542392293023, 1.1564370361826608, -0.37973394592245707, -0.28496134195793843, -0.20331995165528102, -0.077927476498518805, 1.830101752790471, 1.1086664997743747, 0.60211686511062867, -1.2242103389483379, -1.7755134372314143, -0.73018443402509214, 0.11605796445159614, 0.17252420379464431, -0.41382347200302488, -0.84639820657922094, -0.93858117156077114, -0.65375552419146099, -0.43886935578502506, 1.5826322453131483, -0.71196191991403901, -0.56178152993048458, -0.63886868593566581, -1.801934543469472, -0.2205539336275619, -2.0968384216914071, -1.5594231805814445, 0.64352688691937476, -0.09440002918838275, -1.4940996343609763, -0.68358338418066689, -0.75314395758961983, -1.346213077517602, -1.2022581549579565, 0.49339444183727327, -0.13425579818533825, 0.012231691795277787, -2.3138278035818809, -0.087326869637765564, -0.90477403582618487, 1.2594071140608483, 1.0600216323986547, 0.14782373089563422, -2.4869473247019429, -0.66268486522083803, -0.66832415393623501, 0.15983198827812892, -1.5843147122269146, 0.94926689829035849, -0.10184156673806151, -0.37843676976534996, -0.66592157304513322, 1.1003869375523752, 0.32835780081030802, 0.075845478737941605, 2.2501878827697079, 0.64480432449820368, 1.3247006085394253, 0.042175337800861377, 0.63488851760700471, 0.6166409891277006, -0.33988214174963227, -1.2831906972117368, -1.0580213103856495, 0.22801470421293024, 1.9451548197249229, -0.72731297326465738, 0.057264581500404602, 0.2773147277370458, -1.204521235925132, 0.7158013690850159, -0.21984159051271088, 0.38133020274390961, 1.3373785301939314, 1.6381670135604507, 0.11956918157278196, -0.47843800465888076, 0.36126323568779534, -0.41822473554021888, 1.4656708462068881, -0.37344502134125956, 0.23443837998758324, -0.50795766935786335, 1.4999961766508016, 0.4105711715785737, 0.065381840516438069, 1.0664824328916824, 1.2404085981501722, 0.57160494559576114, 1.05831292799342, -0.32678420822141196, 0.58493037451605434, 0.75445959443301314, -0.081293131459115389, -0.62873997846100105, 1.0251224259591649, -1.294900277779917, 2.0510684765929339, 0.15521744896465145, -1.820914986734308, 0.50724875950707005, 1.2869416447939552, 0.43764698966136634, -1.7970099350139594, 2.5314626989706341, 0.06039076349691553, 1.6100761549315692, 0.24985333612675234, 0.29995602620220563, 0.17457515211672633, 1.4903043069840112, 1.1163285036396828, -0.25457782603049306, 1.2708156546356253, 0.53539237491186109, -0.041903509481444126, -0.29949932926534706, 1.5317453405353401, 0.57001082620951549, -1.4559946949044058, -1.0531852229715459, -0.8367632529117216, -0.91639056473604041, 0.9238981084555371, 0.10388919692066199, -1.1804192677562197, 0.40929154251015293, 0.52157670710239368, -0.94854412755709949, -0.52614689976341955, -0.097216182945508461, 3.0972514944022351, -0.94575124994962056, 0.09492782725452717, 1.0939539953446038, 0.74225195278308331, -0.62900352935809545, 1.2331053205673974, 0.49205846417108284, -0.6690416957469254, -0.17479384081327606, -0.93511036273293568, 0.83556968491632688, 0.1771436296479012, -1.0809243236010433, 0.95514622939567018, 2.0777651985861785, 0.0016405422169802231, 0.58298150280414773, 1.3093324816012299, 0.85418834030472224, 1.2782257143262858, -0.31247352030754366, -0.29300278941725733, 0.20737808305245967, -1.2236139547320104, 0.87541516424256538, 0.024782098427744662, 0.70782271407756436, 0.60028601587774288, 1.3191439718533788, -0.74728329043896369, 0.053291157031823612, 0.17553748029287441, -0.24856435309261168, 1.2456342513954686, -1.1046507534793351, -0.1899143204884394, 0.040020019453349168, -0.77944713116161213, -1.0545290289144877, -0.07151554311973142, -0.57832195392301766, 2.124829389781016, 0.59636845907364044, 0.44134459252682551, 0.61957206290319067, 0.96338199175064598, -0.18520873127778156, -0.28497836647397479, 0.54051527368743146, 1.7626457267091882, 0.22874978239675012, -0.039690604750721163, -0.64438405090446293, 0.00024249949197269958, -0.50303662707934749, 0.1730200388639638, 1.1313186900746131, 0.1808008407366439, -0.78645629471783141, 0.29008494160117343, 1.6863355967018636, -0.022197012281197134, -1.2689014208300313, 1.7825431102172495, 0.87103181970555166, 1.8755735571092242, -0.53857078725623253, -1.0943662662179892, -0.013622050206516915, -0.74452324634407629, 0.30507533357000072, 0.67045217978790461, -1.1528578826381759, 0.091991823326778938, 1.1253693131935105, 0.63534222369200766, -0.58206804352786923, 0.18769401965091501, -0.57112811180306433, 0.3976003546182687, 1.3809313746892649, 0.73322262716367692, -1.3491926765997135, 1.7307389589111868, -0.68643158721940822, -0.52069513042393933, -0.938851541076687, 1.0084833974838947, -0.95392202810971127, 0.30395343698007027, 0.24593126784385622, 1.3170385397072584, 0.66873855534345239, -1.371971131564713, 0.815190389339431, 0.20795036086775762, 1.611622117983841, 0.45220310333666974, 0.2605040149081429, 2.2293777921874796, -2.1753539210318005, -0.80760075305542089, -0.070066349727869071, -0.44908815102177563, -0.12409435341785968, -0.064989855690266829, -2.7121302505336282, -0.23553015515305772, 3.0029768475062291, -0.53786443631341063, 0.35428373240060868, 0.15177228663246561, 0.019481012021176306, 0.97047091679765785, -0.073203717397515716, 0.38676228415040903, 0.19272661368387625, -1.309014091342922, 0.70754604734731752, 0.40098960273026746, -0.015621752318771002, 1.2873610035557117, -0.15067992316202899, 0.83265326437775444, 1.0124027796692023, -0.020648659572581281, -2.1896156725221507, 0.45618814005914365, -0.12103934751951212, -0.19361147941542159, -0.36148203767240322, 0.67713730786552784, 3.022514397734799, -1.3873608480425694, -0.24093495199719284, -1.3502315552580377, -0.59361479681166662, 1.8058092141030544, -0.16050558724928471, -0.69653467794806823, 0.15171096848041588, 0.39525063477006611, -0.56604794808723191, 0.93518057571807045, 1.3993652871973372, -0.12609472106551692, 1.05650453494771, -0.6491387797699929, -0.62997337691360145, -0.77218809959970613, 0.30871069065643308, 0.092617878662811431, 0.19070199499734647, 0.90859786038223711, 0.56333708212139499, -1.0065737210962515, 1.4377864277137249, -0.080883484772270614, 2.5838265276687249, 0.057271181530981097, 0.59233920542084795, 2.527963923001022, -1.0951136688276748, 0.84518545279213331, -0.65352735042026855, -0.70084189941716424, 0.70107676620109072, 0.71875667651570063, -3.3883615328963788, 1.8663230536067739, -0.46831280513076723, 0.84086955048764234, -0.48779566110394884, 0.29982768290504958, 0.25707814900566239, 1.4947280700567407, -1.4239767670851509, 2.410181448544384, -0.062964717143833088, -0.40698987528751662, -1.2346033584095739, 1.5126034400778834, 0.19299426937851219, 1.4278907805019307, -0.37714413106822581, -0.22594056165029111, 0.41719330922522357, -1.6391973002352931, -0.072194374605339048, -2.5429553869086678, -0.29713631494398518, 1.3439386217983498, -1.8360870006498684, 1.2182217216108313, 1.1824337437188146, -0.49082072735713406, -0.15641588927684053, 1.2130679924706724, 0.52265202622505902, 0.70925105750893025, 1.1639132375928274, -1.4784972583618201, -0.046630155571961672, 0.27048186793355583, 1.2090374385115363, -1.340116692927724, 2.162347383947393, 1.16289068308268, -0.4142451731281579, 0.54134744615448205, -1.2545143380516532, 0.34735802165078117, -0.31996144118754072, -0.2968531836972565, 1.9973753977382818, 1.0471750942284428, -1.5433164482421822, 0.70359705913750847, -0.3116573570095062, 0.49441730471949058, -1.0586975497721696, 0.68890233430103065, -0.37746451925441354, -2.5275330315158522, -0.43495866583616694, -1.5752473734022892, -0.62868010983538525, -1.5529661249623665, -1.3648304551770898, -0.16841646655984144, -0.31600189541435558, -0.75970533896069636, -1.1414568502503539, 0.37432959067081606, 0.025500493822781651, 0.58242699307558687, 0.28528715509937697, 0.44107436970614322, -0.49554364026817643, 1.8233796182454602, 0.99188120591313456, 0.069240773860239871, -0.65119121433201055, -0.1416334259726377, -1.1644907061363505, -0.4265526943498309, -0.030260890529409432, 0.7864129936910752, 2.3177624506582499, -0.93928095710661785, -1.9398705112028676, 2.499019318208358, 2.3503525767722135, 0.023440535885595092, 0.93317407512003536, 1.6933753197600305, -1.9725966039595413, 1.4796832552467367, 0.34005839596458509, 0.98267575884438074, -0.80083956585712057, 1.6933876132220052, -0.95633298928735255, 0.87043302896250196, 1.9873960423469978, 1.0379748458290798, 0.73751646735312382, -1.2009232532986807, -2.5402452807010141, -0.45362529352019126, -0.036064392949149433, 0.8078581982355636, 0.33171602295779784, 1.273420045596046, 0.51482038065695623, 1.5246374937848319, -1.792547323660564, -0.54452283711227289, 0.21471633323576964, -0.51464774229258181, -0.3690385364311406, 0.49800675849614684, -0.95043891232374456, 0.40721731564939706, 0.29836531628604657, 0.75745011997019296, 0.64940050221922563, 1.3048242827758736, -0.61327253221533273, 1.066093534679754, 0.69389824397047484, 1.5740174747597711, -0.729713989525687, -0.20537932357093547, -0.97088790390026658, -0.59151091785580934, -0.26190977232394602, -0.33666866108312798, -0.92122511509883387, 0.68180102512113372, -1.3338531365219519, -0.68105550988088859, 1.081586218020717, -1.361796947772272, 0.019957650519214297, -0.3121490403624958, -0.25647062261766157, -0.48492623104808058, -0.9307389473045049, -1.9796397193563338, 0.61459296639344696, 0.3394855169964322, 3.0531137968986579, -0.14163388207037891, -1.3136855728821879, 1.5806977839537051, 0.98179377193958672, 0.70602918161445671, -0.60881588728292446, 2.0905634948725678, 0.089646283246571479, -2.7984042175440962, -1.9572470839106522, 0.9674895609829427, 0.565398247810042, -1.342072672808825, -1.6434262890565301, -1.9434805479991135, 0.21241534798551592, -1.7118665818815866, -0.47385623107591007, -0.20260023752663506, -0.27752945716989319, -0.43284714128129448, -0.44303217841409825, -0.1804898812823742, -1.3925417628857037, -0.47249624979006838, 0.49129428999847474, -0.28538527406071729, 0.60040867255240471, 1.2191234889225497, 1.3304824439082614, 2.2179021968082933, 0.36350252285321566, 0.23267675222287329, 1.6068256353885444, 1.0575396781854718, 0.095302982494270466, -0.12236851806444286, -0.1278206719589158, 0.99495493485618969, -1.071795778596937, -1.6321824941151437, -0.6953593909742426, -0.005492999394694705, -1.8582718579574817, -1.2010862373919515, -1.5932211588020442, -2.0439433217710645, -0.52668457333865304, 1.5921015181303824, 0.063453896191442608, 0.94800733732985321, -0.4070176294888519, -0.70297075386628083, 0.27963570067806887, 0.31177120623773685, -1.3346909671529443, 1.2898047169030646, -1.4740112188239463, -0.15599742024079952, -0.72966480504936837, 0.062211060830997617, -0.075461268787689967, 0.22611797198622541, -0.5666192108581436, -0.01124040719756984, -0.44449013683295824, -0.17392154463288179, 1.4024944226188125, 2.3563747582525698, 0.22598120456258375, 0.82568121739773725, 0.73018910771945922, -1.3555173777490324, -0.75164273493266154, 1.233105407994973, -0.55131312216300432, 0.17215690612511542, 0.30573346118205968, 0.43575627572912667, -0.3568659974464351, -0.21650489692709105, 0.56645997381993696, -0.87528781197402261, 1.7899746493031841, 0.51168809773610846, 1.3729598865741168, -1.4034782729545749, 0.71289442986327234, 1.1911631283130129, -0.4982725657005439, 0.29116605954976094, 1.6351973647065141, -0.18446163632823431, 0.45693078765263762, 0.96456122113031129, 1.1763312946223041, 0.53090360248113133, -0.48999416658891704, 1.7596222254685614, -1.5773413349652465, 0.96342879405546744, 0.25159826048788703, -0.45124140453059214, 1.7302748758272204, 1.5936964180991597, 1.2139725359788307, 1.0895865772911635, 1.3053735735357948, 0.56029229821087823, -0.95124457854427169, -0.55775570919561634, -2.1187586295703462, 1.4045273826812477, -2.3956072318189827, -0.48928721733750286, 0.23134763531038288, -0.47217693234896035, -0.69500784383430425, -2.2728535600462658, -2.237124863683376, 0.4108669877732381, -2.0624624476072424, 0.45077899716396735, 0.90476496221935176, 0.1123692260494624, -2.5026419914970428, -1.3849249851417267, -0.53265059306452478, -0.4937173774748852, 1.0392062559271256, -1.5968442854419924, 0.032427879932432464, -0.64708245115087426, -0.29032614562597503, 1.9282624686530117, -1.1629766489042672, -0.408543671053755, -0.28810486878568775, -0.73221591755578042, 0.044342279557155306, -1.7201765499170112, -0.51160233290684043, 0.06962548800218897, -1.3528474912628865, 1.6751017575668123, 1.1240717133331775, 0.97488726365807621, -1.0291302956441195, 0.48435363953911958, -0.15733501073616762, 0.58006188984296769, 0.40893891908632019, -1.9780145802869131, -0.14359432971148794, 0.80586747691625293, 0.57663377660683957, -1.3736307925808493, -0.66130523753551884, -0.14665171205501187, -0.60927871426854141, -0.882752245695829, -0.98790625792957587, -1.2389177679526793, -0.86839390942663408, -0.43857655144223107, -0.25916187079703462, 1.4644207677433769, 0.55135890219907679, 0.49819554228840901, -0.15381637415875588, 1.772271788744175, 0.438485559811916, 1.2576720791938802, -1.0003711351549569, -0.55516955787347599, 0.19615179379549028, 0.48126463363782551, -0.22017394700087903, 0.58399806379771713, -0.96934963489939341, 2.7008288715824409, 0.92746065624395901, -1.8807092792660653, 0.74976960267801207, -2.687822801691611, -0.13829215454772648, -0.85650098475640868, -1.3631176299348791, 1.1464813849796121, 0.53565026804222371, -0.75972331678141125, -1.4309307028097324, 0.2001672295530536, -0.71270685884297802, -1.8494886018709662, -0.51210523870608826, -0.13468061500930226, -2.3521899616190365, -0.25322699345695404, -1.1329560120406443, -0.045303888222652973, 1.1741516045258735, -0.076734708565499049, -1.7548865047449995, -1.4419316135645921, 1.685107882695676, 0.49311682555869846, 0.25749855215855749, 0.036489660625382191, 0.052275482466702508, -0.14037144038716595, 0.84598921974074281, -0.092749152701067969, -0.82151033271511897, 1.5531173036209931, -0.68360750662582082, -0.72592570456203054, 1.8577760371766023, 0.88897255329343627, 1.1241756333675181, -0.54889368163172259, 1.1827689056311887, 0.11736691919405601, -0.74345311905573352, -1.2167106169672934, -2.2238226655670608, 2.7650362348093083, -0.83967129305964727, -0.25246796175449482, -1.4985411514845066, 0.38074941330160755, -0.030697210551968872, -0.18767386570015868, -1.5335306915072218, -2.7412787864068822, 0.81700064040486287, 1.6368453780912471, -0.076904821954925776, -0.74174364575733542, 0.22203249573523615, 1.0792650376586321, 2.0794437052436554, 2.8708457524195174, 4.2722991780709858, 1.5488710173159843, -0.036998813391576318, 0.47859126471931912, 1.1972716286767706, 0.13204094357608767, -1.3330297500328399, -0.64728417538565353, -1.0842977859687224, -1.7223205032640025, -0.59272823129741048, -1.2409504694752613, 0.010237149916050627, -1.1552145492445201, -1.3326462362466673, -3.0603445650817931, -2.6187556937787799, -1.6274752511819153, 0.82540508062546569, 0.72743862721248864, 0.87181684789350311, -1.2193054879581229, 0.12949375367775273, -0.15019821081379911, 0.14235939347792839, -0.016453320836381329, -1.2294048741515626, 0.75675546415544936, -2.0051017518470164, 0.48539804262446962, 1.8550631833439548, -0.89394278771608437, -1.3853691484927464, -0.55463752047168258, -0.3192936451425854, -0.79682458074311791, 0.60206972502858058, -0.56385195178802905, -3.8812328052735459, -0.97710855994303769, -0.6583046641124809, -1.2428687695122891, 0.30243326611792182, -1.2325566929104503, -0.40601298173254136, -1.2706089734384964, -1.0740203377614583, 0.37843071234444497, -0.9314291454683401, 0.87780090643327713, 0.96024922789479816, 0.33619544993706574, -0.47275480340691961, -1.0577068291547425, -1.2177373357527681, -0.61519258576918345, -0.24131405051105334, 0.35105537456883878, 0.55772062129893374, 0.99000123613071744, 1.5013635695241847, 1.4488993131511425, 2.6419013998081202, 1.6878022840463207, 1.4761524296399602, 1.000843271504305, -1.4042315739091544, 0.010729873612401625, -0.33014884340430339, -0.51741714973411446, 1.3349115162774259, 0.66092509724496473, -1.3934306520311714, 0.63474131554628033, 1.4819282496902384, 0.98541415826061318, 0.94719909120228396, 0.74998356693042634, 0.312487293549298, 2.4017718536067232, 0.64609850249825618, -1.622493925952684, 1.3723743683014697, 1.200243390103324, -0.73079598265565437, 2.0549568094181057, 2.075682747446308, 0.28183671302154872, -0.336808636447749, 1.51117177314978, -0.28438570261405438, 0.83324039599455979, 1.0608668001393859, 1.4505881257551743, 1.0399682254396587, 0.33728594906218301, 1.3363563149382007, -1.4887831997464933, -1.0476266217355235, 1.325343546136895, 0.9701919356306189, 1.0244811848839521, 0.34021701102629265, -0.46542866640610342, 0.48391727322256872, -0.39269585117938133, 0.088775089616129441, 0.036559233032017517, -1.2790366765564598, 0.16413432230538882, -0.8228193286383495, 0.074580393099911726, 0.75452143774309088, -1.5529306207042521, -1.2003488982211188, 0.91888110108189835, -0.35742664806137958, -0.17019672678884343, 0.86178293285246865, 0.99925329205632019, 1.3400995897341466, -0.036134893803763481, 0.70794938168778043, 0.010965303374638167, 1.2178473690924432, 0.32711540510926174, -1.0389230463237251, -1.0856926973251961, -1.8880111297800175, -2.1875006224003095, 1.5715607650248347, 1.6175567112729903, 0.15866783401097809, -1.3468920075939042, 0.2498788646925019, 0.0080050582815557273, -1.1468580277016376, -0.45984912136118949, 0.2986214737229167, 0.85586586470047255, 1.224175271302385, 1.0152749920776725, -1.5515666736692835, -0.28433303938549387, -1.2002144798395755, -0.63583412311906951, -0.22295668426505896, -1.1453652309559237, 0.75139158724667909, -0.16441847161792411, 1.3312926410314139, 0.17938475178338692, 0.1252182117640156, -0.005456962150283403, 0.30075088129469335, -0.63956657403342998, 1.4395463619413895, -0.96767828520353094, -0.44282822787106585, 0.52302847308983402, 0.080645368332212697, 0.45812075885582021, 0.34256766595863919, 0.48750334858551742, -1.451792910633064, 0.10187103673071035, -0.79682570345980708, 0.11032406164073771, -0.83766705876345737, -0.68683201409448769, -0.30499602105030371, 1.7546958697246284, -0.40282941233283009, 0.53024182641965811, -1.1716084086031666, 0.65056570642324973, -0.80632107803565822, 0.6392908300731539, -0.26111827856526831, 2.523114518344189, -1.4080639325148798, -0.44798976235448962, 0.11958114994407486, -0.61764401538696501, 1.6930294063125262, -0.93588132037164118, 0.21475128325754012, -0.12521981889066547, 2.4501679794605602, -1.7168303836432517, 0.80261124539365181, 0.60788241779955987, -0.75936781242757823, -1.1908665432339556, -0.2163189366829967, -0.019696867307362181, -2.0756419399423369, -1.3687896537318394, -0.091370481919775356, 0.63929184145101015, 0.37631827205660695, -0.35563308143467148, -2.162380220331396, 2.1413080457944527, -3.1234358996248783, -0.60559457730388333, -2.0861967327219237, -0.17454111068868491, 1.3524088098643392, -1.5233534696158024, -1.0439085877662078, 0.030817207943395535, 0.72401412303413615, -1.3990074007074009, -1.0751641494982602, 0.47036459476411752, -0.28399589813985998, -0.93518512612314031, 1.3842725531550732, -0.059200795094941215, -0.7841795399010959, 1.1500414558581582, -0.39149822790301425, 0.53629544646607885, -0.69901617562190921, -0.8152783574235466, 0.88329079603494032, -0.010108756044479653, -0.66427985599771033, -0.070023571702536119, 1.0172949138508331, -0.52694608147751665, 1.0367654002666378, 0.074496475243273158, 0.58450466203251239, -0.17431169967844828, -1.3010218242296103, -0.73391094904428955, 0.84210738217958148, 1.3935288906779257, -0.17965214101090773, 0.63454638141461706, 2.1565586064570721, 0.13683644675396331, -1.2570477636476132, -1.0522261914794131, 0.2765576656570623, -1.2153829518489283, -0.90445939622806626, -0.55086799027832267, -1.5990010341079044, -0.95458473448005898, 0.35534137729075094, 2.5779737872001465, -0.024883788220666725, -0.63060517758066859, -0.3426657030483935, 0.15238912548366532, 2.7472847709592108, -0.23801130912357391, -0.29919772978652859, 1.1299586315331329, 0.17585972753551563, 0.69342383458124812, -1.0207715537053619, 1.0153674916566333, -0.070753177271558762, 1.3530757478395037, 0.21249322946339019, -0.37302677698473907, 0.93623099864982451, 0.36103790051849183, -1.9716770979097324, -1.4555629272852197, -1.878444852540254, -1.0574726349991732, -0.6213042664699735, 0.6568497267248401, 1.6462484260753818, -0.25097134213504574, -0.45645031530505886, -1.309128996845311, -0.38420739850164437, 1.2219409615867465, -1.1065591628737805, -0.31171066070987224, 0.50521470450284611, 1.456488058014489, 0.88270281712231191, 0.057877385249517702, 0.143871610790341, 0.38267912750056365, -0.69871919150380657, 0.23031411739952487, 2.3365660369894439, -0.54254764224210217, 2.2099997382855077, -0.82836233080098487, -0.010866732827382529, 0.42547970467967683, -0.46118466466810032, 1.0144672794698075, 0.7566171053437093, -0.36528613797181525, 0.31815476498773287, 0.95821064330410588, 0.66259170803714995, -0.19239592353791476, 0.23104781342730005, -0.12056842782191918, 2.621497409516119, -0.01486795347787523, 1.5778746875517284, -0.073011175205027243, 0.75892593212610593, 0.55884443717365029, 1.6551078244490218, -0.71666457185604038, -0.27320050467637258, 1.0124592366711751, 0.4126104404761638, 0.49103376304471824, 0.81757906813416303, 0.73538472160612633, 1.2570997709076144, 0.13883068535180668, 0.73947477203810064, 1.2354582316500164, 0.37441154433836937, -0.48675493518733726, -0.6575311062677387, -0.24424502631293243, -0.66414178178970884, 0.40878576334969935, 0.15588115225587373, -0.40268671322338151, -1.2798258880237106, 0.12774436742439341, 0.17195146731165131, -0.16861051110506012, -1.772489994167453, -1.280186098818435, -0.60075638239147244, 1.432418214211076, 0.092148443820253029, 1.2296264885636536, -0.0045018252262847124, -0.75332514899973169, -0.6204283431172577, -1.0159228473607147, -1.2966446953354152, 0.42158186918843965, 0.030904262510015303, -0.18178936478511767, -0.50017001507322367, -0.37999501969180532, -0.51655254897174341, -0.98922162653383616, -0.83595595252963284, 1.6999593941027837, -1.133749967767782, 1.6658802420148491, 0.39425455374445628, -0.76550210767499649, 0.57970069493421383, -1.5358898518992936, 0.055489695205940041, 0.59768133945033397, 0.0051161094356954309, 0.21556576700311755, -0.00030774051242014774, 0.92021730184167183, 1.1407388478017113, -0.091419392824046569, 0.19969238923361241, 1.0325192449935789, -0.13848223612980151, 0.20704224887147754, -2.3665412670323138, 0.23029278613624987, 0.57588983268610006, -1.5012225162261448, 0.014346268264824826, -1.9665641322589178, -0.93691118781262983, -1.2390714635275835, 0.57718643151331961, -0.74106576988040396, 1.2829179437523592, 0.49678108707712237, -0.93801421757733106, 0.40421157304267408, 0.53414435174234642, 0.040415851375578349, 0.87230764675776351, -0.098692579706718631, -0.61253495446999473, -0.23174226676942208, 0.3016919917280183, -0.36244992943041926, -0.57788318400569394, -0.1726752759637214, -0.34712773704580779, -0.38449050091247322, -0.15830602457234191, 0.37083980864351729, -0.56720286105824058, 1.1839105572176341, 1.9213811658174522, 0.77466056270060557, 0.60672069423881325, -0.2001449512122607, -0.10074300033790504, 1.337559388173194, -0.14113336377619307, 1.3825493092271461, 0.493595626438664, -0.21301114978187696, -0.11638927589496463, 0.85878853477698303, 1.8584869606236931, 1.4240782296563821, -0.20721875601537768, 1.3686198286275277, -1.0703130238374461, 1.0239715490788022, 1.096361523688381, -0.99001855421716256, -1.080271807239823, -0.60689369586353425, -0.52070193172640056, 0.62351255183756593, 0.66453934841685947, 0.31689801019787511, 0.20192687117297137, -0.15644043966527763, -0.84110615519756993, 0.61311377123026234, 0.036021943187133879, 0.38987439344316371, 0.80333377990831334, -0.93490164720014968, -0.27593353585617603, -1.1744443134360378, 2.3586430524794992, 1.8800178518716066, -0.84530434752292172, 0.39464786092174758, 1.3802521724896639, -0.37350040910867055, -0.96092997522764378, 0.80071826154952053, -0.49617234699564161, 1.3656780093628043, -1.2002897574830458, -0.0037982223720763202, -0.054876147558813884, -0.56087565731845479, 1.1946946581987616, -0.25050142905929973, -0.79550159747763405, -0.04786205726188987, -2.1637766750786604, 1.2123694140109929, -0.5173104499803246, -2.1112012708952701, 0.51481604934521352, 1.8889722889948541, -1.0328743193039678, -0.19232767116612551, -2.1945829720489298, 0.77918919632300865, -0.11213546307143975, -1.8050470710680802, -0.29586136868196455, 0.57372705229157539, -0.42231903687623551, 0.94308363904330927, 0.91116115233135708, 0.13750352193709681, -0.21628356006850449, -0.68749061554314828, 0.53600369576148377, 1.947658164267561, 0.041987788526349136, -0.5368685826107078, -1.0184116701841996, 0.61475986097890256, 1.3283658330925705, -1.378792504716188, 0.43999735166123344, -0.75587549448528468, 1.0703147410928031, 0.20621235329343846, -1.5576373666555838, 1.633211219721137, -1.8927164019334466, -1.3992119956403761, -0.33699131344750366, -0.96406494369707307, -1.6343394323859359, -0.63301732666164645, -0.97073283838394719, 1.5913393154135536, -0.52986928004182177, 0.0022826826891175246, -0.64895264929162544, -0.76929147504381501, 1.0332910341991834, -0.25185256790559241, -0.38978686549508884, -0.53950791794904607, -1.0843281545752677, -0.60646974154156763, -0.12294200457722498, 0.27940811856201381, -0.48677403435817007, -1.7085379410729373, -0.61945034969411383, 0.80249660771613529, -0.83168157507145291, -0.63420066048828216, 2.0618476028072821, -0.092720269570913713, -0.90262856139340042, 1.0889909142317225, -2.3664147145008663, 0.31640563717148201, 0.96948488982751069, 1.2596406036544567, 0.83141916158893281, 1.3584744718906006, -0.035463245072656163, -0.95588589726251638, -1.110839086060472, -0.0092836582833674599, 0.024108036892989369, 0.32116377419379888, 0.38700129077457773, -0.7177866770776129, -1.0774229719550339, 0.50944464182570248, 1.2242501081618284, -1.7111810696857002, -2.4859154357367079, 0.9538584100111428, 1.3903405922206296, 0.31811855624928115, -0.23109039881938406, 0.74055576605860107, 0.99545578290703773, 0.49298186256521381, -1.5651330246387576, -0.47615172577696474, -1.4606488532946094, -0.29025744690597099, -0.67141679260947829, -1.1412062174072108, -0.00038532164463658933, -0.54638754686222268, 1.6156833815400677, -0.81475861479239942, -0.15666635718720526, -0.66996510862919412, 0.39944477847778276, 0.52869012383245628, -0.93871220110488407, 0.24492223679217803, 1.2563943989840716, -0.61428924395305584, 1.1882969855527163, 0.90858102440388322, -0.13118174342290606, 0.79147060918070999, -0.41009293663861529, 0.70995011083241166, 0.19827813832756191, 0.68259094653611629, 0.79992110868763655, -0.73275021574878474, -0.52363921788166179, -0.35133745135849775, -1.4152658971876766, -3.4626658676037594, -0.45968210764595346, -3.1024485432033648, 1.4937769414754991, -0.53474250585275573, -1.0564478779283841, 0.8906063417679918, -0.79824026612037213, -0.68996998565423273, 0.78120125386653338, -1.49247395931061, -0.13320525547726139, 1.3769848466487169, -0.86495341215269628, -1.6925043138184321, 0.71131117568392721, -0.5765780252089111, -0.5161849314843503, -1.7374438820896489, 0.95573636041562093, -1.8478424601546251, -1.7007199994527307, -1.1063991545392107, 0.9011420473204137, 0.15943365363616008, -0.29940129306532759, 0.0037239216413178077, 1.1214415724407076, -1.8098581766459461, -0.49580580047647976, 0.3519081650684498, -1.0213254281653434, -1.2092935222199783, -2.1070529661296504, -1.1811897346694968, -1.8738520901891027, -0.090521815393353203, 1.5223803050696583, -0.41839226500564075, 1.4510811366995022, 0.97694050212190309, 1.6073997282876176, -0.9455865360727288, -0.33031820672071249, 0.38824213291820781, 0.22241647789853894, -0.90444198581147173, -0.61584703711452238, 0.50768091338665711, 0.86515525601083076, -0.7499133968881625, -0.90589092702949892, -0.8321006553912228, 1.8525200754192712, 0.09387810961470025, -0.28778282339824812, 0.92429962339102723, -1.6223284968400526, -0.967721065455596, -2.0456549472539218, -0.8385168732684336, -1.3356073543342164, -0.029555779816975523, -0.72477965981417314, 1.0356273026691512, -0.54831266142373181, -0.029094906737467181, 0.6677588895905614, -0.31921380669329869, -0.87877208779552507, -1.4687937454377835, 0.11368501660184333, 0.0050515772811941771, 1.8898799593348508, -0.19987288675493689, -1.6994083605455663, 0.13616486728410362, -0.91821274323149171, 0.12643530819915946, -0.077165008800378368, 1.3713668146772202, 1.3511703657755381, 0.3788553789226915, 1.8398289028519998, 0.89359857395839137, -0.6940869867826881, 0.40600964839080522, 0.55503783508373905, -0.23134665657527162, 0.97088540071919405, 0.92140640813204844, 0.49043554928950966, -0.46936868601790993, 0.49547312655325654, -0.43519536253094987, -0.8478933837375292, 1.7037635913624531, 0.49146454156786823, 1.1647317620314934, 1.1019860826949919, 0.69014374466381723, 0.67606301997050444, 1.8387775718831239, 1.1517480514839316, 0.10159102976690075, 2.5888468964075471, -0.91774828466069314, 1.5264732293877847, 1.8267979932848719, -0.63481160681900695, 1.8182584002153035, -0.80108527822937925, -0.10243822304661927, 2.2080085027956811, 0.01622895818489787, 0.84086357411810531, 0.85917860725533191, 0.67569255877771361, -0.71992228614115417, 0.9783794400824638, 0.63776430964126973, 0.0037803595670037292, -0.94330682945135846, 1.5599547782404686, 1.5292262793530402, -0.48901307356194157, 2.7247750774943955, -0.57773941943544393, 0.89340862926688758, 0.80221437320478806, 1.0547696375424089, 1.4417601811902101, -0.36267866284509309, 1.2493212346880072, -0.039096821120387905, -1.3143459183152901, 0.016173960510005952, 0.56531672140417522, -0.98737826774435078, -1.8531159780057807, -1.8753152543145699, -1.8956283101043274, -0.53028018002788813, 0.036434810330761486, -0.86127357250029402, -2.306673986987247, -0.85125463795358169, 0.17250512300896581, 0.44902791234248157, -2.0346531800248777, 0.40128331985850185, -1.8810200435645741, -0.23926185669263891, -0.7759064600051534, 0.23933174507621602, -0.2172964935547341, 0.31735758165642786, -0.3091013601444183, -2.3222204946210478, 0.15914456666059365, 0.092014636046210588, -0.84329225849726219, -0.59070206543334924, -1.6833636500060707, 0.36082842124631165, -1.6185640146850344, -0.92499789668988663, 1.5082939486527527, -1.6823643359372933, 1.7488402385930983, 2.3048236601927714, 0.46074109821405002, -0.2116005517005364, 1.809658134889397, -1.4320500057599088, 0.54373016523488005, 0.17521148897546718, 1.0679411660042801, 4.0685146201843683, 0.030177241108883424, -1.1529079131904607, 0.74401582701365088, 2.7751861445145876, -0.14061419701633629, -0.19967441021590496, -1.9622577098624032, -0.41676656133159296, 0.70165052988207266, 0.66038846345492785, 1.5444218519954744, -0.42896831367487709, -1.3341952381469557, 0.62726650876230527, -0.01280232302845756, -0.71345534443970438, 0.18495609051221362, -0.32633166979770412, -0.21636169346380704, 1.2168642626862649, 0.63198236424725474, 0.31328353237579076, 0.53239382382221823, 0.67092398760111072, -0.1831934349829854, -2.2763180749321741, 0.31698082275125855, -1.0889107218927576, 0.56389368026960507, -0.16941960130843556, -1.3251643290949879, -0.98592930047931449, -0.76158220861723613, 0.84207936724527466, 0.25243942459601287, 0.35805488711082517, 0.90127205447570991, 0.91597355094672939, 0.26425441461501203, 0.61011123157139857, 0.82690763378187604, 0.37759698283516901, 0.30181322691460355, 0.88331019727830318, -1.5632821996361184, -1.865583244140544, -0.27348163042981033, -1.1985404031652105, -1.3754871801153279, -0.28723428568521436, -2.0191496321836273, -1.1249020387874034, -0.85799719003877928, 0.73349595058644013, 1.0498898792759046, -0.42411194321175733, -0.51037082562673275, -1.7285280159170897, 1.1525795821658313, -0.10990638201342663, -1.2234519497874721, -1.3253285296000867, -0.34860368653904233, -0.50566865065628885, -2.2607684379650967, -1.565558215739111, 0.27866475545704433, 0.69481682855161364, -0.28404881364582363, -0.72451680130982332, -0.25944997006884379, -1.1827056627230328, -1.4827535209509293, -0.36994848232822686, -0.72578631441070462, -0.47160816519995696, 0.90135514179792831, -1.2457868285882661, -0.26510382191942933, 1.3797810984925261, 0.77370759544138623, 0.73715118346802011, -0.9070225369791074, 1.1130245710312472, -0.0056948256355603801, 0.072831885797518842, 0.54095119428942839, -0.25866162644519819, -1.0313841683683331, -0.73332123932736915, -0.23286908615476382, 0.7719562081384429, -0.058033617820043112, -0.11191674888048252, -0.30097529552643293, 0.059999923989311192, 1.0837607075022078, -1.3132140960975625, 0.22622142022765349, 1.1584318731206851, -0.40738088307807402, 0.70169580036776646, -1.1205162889024001, -0.42545088580385404, 0.20863174463544562, 0.11885548732961011, -0.59492387329152718, 0.65435357937010441, 1.6460704909813744, 0.2107350321332076, 1.8654786339828324, 0.84816034247016192, 1.7754972097710691, 0.32671649403451969, -0.39324186159126889, 0.58178647564325914, -0.09071497384302675, -1.3804057025035537, 1.6838260022002227, -0.08947339062786637, -2.1947421470048911, -0.15392104686844005, -1.3773790053339474, -0.60432036623862551, 0.09344847044947735, -0.7155395261052635, 0.53057762331345215, 0.65132435963211521, -0.15592220977006599, 0.49755343564689791, -0.50436336272530136, -0.51695864902972211, 0.27282757808714442, -1.2092153435466566, 1.0185514742819339, 1.6477031835025424, 1.2567723891894838, 0.54007158266052135, 2.3482907612073523, 1.2217285587697919, 0.15778776229552613, 1.1627495016689511, 0.2858912433115659, 0.21832881463314915, 1.8579883145243237, -0.60005606943345335, 0.59938349296662896, -0.77899366473309206, 1.1560032423989535, 0.074351922125549863, -0.57903878007234666, 0.87833194485029931, -0.35228436621007497, -0.37722956041433459, -0.4421730964071941, 0.42936749859500034, -0.2779177707538586, -1.1638534479493874, 0.97233322216565388, 2.928158954464037, 1.4615191846653117, 3.1394450973031698, -0.098693618175456327, 0.47251158420920947, -1.6424127145345293, -0.30750279008283693, -1.7944279693392859, -0.66618248956006876, -1.1222319370286298, -1.4873037349791884, 1.8182104520568783, -0.67581119609618723, -0.12411007881892723, -1.8776326564622068, 1.4207459544369894, 0.84026181630575747, -0.90452447594929652, 0.86215051698894707, -0.74394700242527012, -0.029263758620348714, -1.1024911706071743, -0.042308520476109286, 0.70449862530025897, -1.8980421132700616, -1.4375718692774135, 0.32204704405402296, -0.86191106467845502, 0.69349914842817839, 0.7654120328100853, -0.49065643786689206, -0.022161286093029035, -0.54364877671836842, -1.4923061439647278, -1.2510271444723788, 0.24494011694250054, 0.61629893099640642, -0.8595058832722271, -1.0574353822676619, -1.0081100652424486, -0.19763159081040249, -0.56501355774243767, 0.69856326054322238, -1.3059177386241787, -0.60542960620622155, -0.12006914013301201, -0.32374516773753753, -1.8210780363103372, 1.061850955793709, 1.8474326055304784, -0.99359761049465145, -0.21208251269351441, 3.5483461324966186, 0.66806653318688181, -0.88990092369976037, 0.4410651702984143, -0.24888840044176758, -1.520206002295438, -1.0332507072687147, -1.0252009959142703, -1.2793663340256176, -0.40944870496123287, -0.21249617670003132, 0.57045915462218189, -1.3193509127360827, -1.1115717839177883, -1.3114365922301416, -1.1217706433443595, -0.87305688103448065, -0.12420503918510779, 0.018775203327136142, 2.1056753627670295, 1.5658558801286124, 2.2012046557003222, 1.2881486016509132, -0.61042721157079627, -1.9749516266338503, -0.95927759229263532, -1.0193964354440437, -0.19950365594359901, -1.7424082484905419, -2.5657411407975097, -1.1790412815153006, 0.60731527836168331, 0.92304435767952475, -1.0769676656793736, -0.36231727823642096, 0.99258467525750727, 1.3456049980301845, 0.45229868241540938, 0.50069578434222972, 0.80764821681091736, -0.4757422007733888, 0.11611707909459498, -1.5181344397202174, -0.75638043128457444, -0.44721982556867329, 0.28929243821083311, -0.78734887018217303, -1.2658131718565859, -0.86841637541668348, -1.4064717675469087, -1.5040083971977187, -0.087891809224211109, 1.156997216954498, 0.60156727070306504, -0.086769938074748781, -0.96721715234684458, -1.5173532802024936, 1.4089106100584299, -0.11716564438286542, -0.21936638922197435, -0.80279946563843041, -0.66456991068174454, -0.51048352078693304, 2.360968557080882, 1.9090678068798237, 0.32612830000317444, 0.72544126075608062, -1.3763870032188754, 0.69320811546740846, -0.80587379009217663, 1.2278621226254247, 0.68589411232525421, -0.49097905989010943, 0.26686999696036739, -2.0205780970855134, 1.6696422657272578, 1.1738095625839651, 1.7951624474601675, 0.98419249520734997, 0.41479479657982443, 1.0265268848055191, 0.22931920043845025, -0.27615983764547836, 0.235823373152731, -1.4094953634920198, -2.2233167743677038, 0.4790474724488582, 0.74846860867581466, 0.57437052351554785, 0.0080853306714257153, 0.13106297476700743, 0.52753069780765582, -0.58075004950479747, -0.22258928429526881, 0.4528600437190663, -0.57042453734044374, 0.6507574118931293, 2.6515191425936755, 0.4473065510979044, 0.49717510679383098, -0.13155774620237998, 0.62144697117541403, 0.53012331810157765, -0.1681019448270038, 0.49751977993507179, -0.78593862721134444, -1.5467230320470855, -0.95478552383356519, 0.86247633131810408, 0.54603949029866228, 0.70014174805765639, 0.48154136513009738, 0.30578053401807087, 0.41455089062655809, 0.37900053172022447, -1.1474430644327149, 1.3972774872050708, -1.6976210290535176, -1.0950252190932221, -0.66079465457365671, -0.19649524128988513, -0.016072312683174422, -0.53805014976950438, -0.84897868060190596, 0.049294175186994298, -0.54794358120147491, 1.2777632156493133, -0.061442320675916616, -0.49693402010574872, 0.58177296170598392, 2.307244847206209, -0.04665157541129953, -0.28855371737948049, -0.88861313420444032, 1.3454174809798576, -0.44712031882941616, -1.0265168278230339, 0.28575344988641738, -0.66482200647934742, 0.75524738872600317, -0.43432180276558591, -0.21536763847716686, 0.27941158609855382, 0.44241831336099025, 1.3404286883154857, -0.21928830462850041, 1.3174438901032886, 0.32111929223441465, -0.74137209921725045, -0.75291078095236585, -0.52388387605773312, -0.45889998842446345, -0.32929495963005734, 1.5190655008689313, -1.0506064219603255, -0.062212688525839874, -0.64672043277964342, 0.96798164831313327, 1.4923548792585304, -0.30283748433472574, -0.018995997264061971, 1.0520509394356543, 0.50622928629094477, -0.74160175607251222, -0.81119380973599009, -0.81617561359432145, -0.2841653186647331, 0.21090844964206723, 0.032281650893860959, -1.597474841466634, 0.33524541350284937, 0.081135943842298816, -0.091204791201264887, -2.9979508035083469, -0.043414254359097869, 1.2873615602988133, 2.1959997106910198, 0.36686544011969074, 1.2387285726194224, -0.2946277214718801, 0.77652892391774564, -0.11462178599952523, -0.61470014011118201, -0.096429368366914792, -0.20228559384062811, 0.32787737722529403, 0.0070294670044075986, -0.45764990407655265, -0.61637746695436657, -0.27998728057875166, 0.52105955717986485, 1.1396882834864615, -0.5355774794776943, -0.77117997128971949, -0.039192695828695868, -0.14193254232939753, -0.50673700289452939, -2.7227271046412271, 0.38527859043364532, -0.61064769476089575, 0.70294781505811044, 0.96826660606099502, 0.73494587895533703, 2.0890476851010757, 0.77343147409906543, -1.0089606693081095, -1.2811163614445991, -1.0855246582300038, -0.59798459381081948, -0.78455585855477528, 0.39912314300355262, -0.30433406782979305, 0.23346378120064021, -0.17900385275554845, -0.23310583326596573, -0.59118403397217478, -0.0042283362415827652, -0.41593306735888108, 0.074299147244169236, 0.28455735853644976, 0.72844713335722133, -1.732566696213715, 0.48708541681211359, 1.4239208751615067, -0.64443531157133216, -0.27471191581686594, -0.91140421125390247, -3.1509144430150093, -2.4171726594099106, 0.09617226654690289, -1.5244003600649902, -0.29628190582623798, -0.045161682301821479, 0.80880128070934376, -1.8668034783316307, 0.041045528182466089, 1.1899389176823314, -0.75953288241264383, 0.074996477675586717, -0.98167382833106243, -0.20618609606070742, 0.97478564077855734, 1.569206124883755, 0.28367277722483625, 0.96946538009010386, 1.7072181186814928, 0.77707028169286785, 0.79158101463043784, -1.2750891637323565, -0.28377792756420023, -2.2889380310330116, -3.1584143610455113, -0.53023238479437584, -0.35007840296109743, -2.6766549527191961, -1.6867513723358825, -1.6697517228159091, -1.6651250351813442, -2.2260690568046155, -2.0849148080521371, -2.861147051256824, -1.9146946745144406, -0.13241868312047425, -0.76005383268385418, -1.5365739167484314, -1.4980913941255505, -1.1726271464366043, -1.7908897105613404, -0.57505995480806582, 0.093392761091637272, 0.56637590205680477, -1.6798669926635119, 0.78475538207656659, 0.58765960137148854, 0.7702422331442923, -0.96879245122191771, 0.28293135935544339, -0.69229768658827573, -0.54474787732088892, -1.449484663725652, -1.0381019218336036, 0.095589478436017589, 1.293360146641567, -1.4535116653053517, 0.78421163265215343, 0.14695135827784267, 0.099996134244120363, -0.40477971786499822, 0.48534747790802796, -0.29579162587585706, 1.4159835798666662, 1.180110243581828, -0.38829257199570272, -1.4398063097294309, -0.68117072569869885, -0.62219374620151191, 1.2352613338025917, -0.55692263314094104, -0.85082348903157712, 0.2673713464349276, 0.79635813218034679, -1.5180473404919628, -1.2488383071700475, -0.42717787099843518, -1.0610792918173428, 0.2255614572649782, 1.3043233361546576, 1.6669085373275763, 0.86905071884275042, -1.7251975574198621, -0.27826312093863015, -0.54420460493179179, 3.155762078371589, 0.2954525713342861, 1.0454992903055413, 1.3295508305747745, -1.0597964193117206, -1.3129345092615432, -1.2609703731417223, -0.13834078939592334, -1.4700222833751053, 0.18032303150603463, -1.5267689527120454, 0.24352600226007198, 0.50773414560770536, -1.2735206829369483, -0.31382739502741608, -0.56467662968929133, 0.15848636173160946, -0.51117425598830868, -0.37866818625098042, 0.28383136959231026, 1.5788238585818679, -0.6722691335359442, -2.4587870038996882, -1.363757866992056, -0.24849532013653572, 0.38148145917157211, -0.37256601709533421, 1.2374039882661809, -1.1701308788927103, 1.6303765597883764, -0.15784985500501558, 0.63311868770251256, 0.22434145403168915, 1.4500044288506511, -0.25189722891213684, 0.17779006077890822, 1.7302223222861337, -1.0421367007514974, -1.4845155545604363, -0.61185615659385406, 0.75629904858160835, 1.6248498584898035, -0.25206859648465829, 0.053091316397518219, 0.41102917048686649, -1.5167666382110312, 0.91234837973640215, 0.076149162286950622, 1.6368168042865459, -0.9527020437678656, -1.8693446616370328, 0.22080957844099583, -0.19622339358954524, 1.2903912730107026, 0.04317093538590841, 0.10383341135882891, 1.9184897040507978, -0.36571717803350151, -0.53831786662223169, -0.49543816124878309, -0.4392360916527725, -1.9209302847700553, -0.023490886134213886, -0.16779957385505015, -0.50857759302916605, -0.80130972762863684, 0.69865963788472651, -1.2594738129522371, 0.74552502374959506, -0.52227191181341226, 0.033435884268421881, -0.24701317969583261, -0.54597641387694362, 0.20468737465141529, 0.29692657264406186, -0.10861218909464201, 1.8037462665168249, -0.98541861780670414, 0.26307694203401338, -1.9802242967500929, 0.12460579538385173, 0.68706650366691269, 0.10293555976955941, 0.80748004584555677, 1.8353208275017605, -0.58794608820853778, 1.3365031509212741, 1.5289640269710658, -0.67474249422854959, 0.0083889321140875502, -0.78749395877733996, 1.3131657830443439, 0.30566142633011473, 1.540131952486862, -1.1335447652643196, 0.49925760677843328, -0.18083782824412253, -2.8389814240011315, -1.1383938064352468, 1.4591230409041758, -0.61426582391439355, -0.67176730506431603, 0.99706300321468, -1.2201091248726839, -1.1961744111320798, 0.044432004042462891, 1.1891259369685405, -0.8923706028716778, -0.062748209164652277, 0.43253993303862531, 0.76099736119628481, 0.69515740984657926, -0.52779299401564583, -0.0089989674606045528, -1.0794856024531192, 0.63843964919657448, -0.19502886527274788, -1.581302248609405, -2.3994556499795632, 0.49148374488167307, 1.6127185666184154, 0.52739057611370255, 0.34647590503556291, 1.2516792211454926, 1.4033400637942388, -1.5621030781147827, 1.1270471081398747, -0.29925842942652375, -0.58198777084333519, -0.76596253193974118, 0.13045085851278657, -1.1219748119051289, -0.47567334814185713, 1.5134258313707361, -0.98539944570210569, -1.3580636111024074, 0.50919114887255312, 1.3898519097825905, 1.0912167437309526, 0.31372167285840408, 0.16588195991744834, 0.46840969812315247, -0.4537721060071106, 0.78821130622115065, 1.3800723690798526, -1.3698628745141364, -0.10515566192847282, -0.92531030704306416, 1.5548409083013219, -0.86837572171275501, -0.50920945678777296, -1.3149358961029183, 0.43791069691661166, 1.0535477354803451, 0.52678428820266632, 0.97303854375843724, 0.25260521273953113, 0.066093190427305576, 0.88688802337674655, 1.0998165987349313, 1.4831265962739937, -0.71605366182391583, 0.4910133790850163, -0.99613771704892495, -1.8815339278963832, 0.25073787815493753, 0.44681312241543197, 0.57323363442853092, 2.8379205894240984, 0.58120419828881154, 0.18849174384009371, -1.5865207977142288, 0.55929671967137196, -0.40114996719958468, 0.13423083391510088, -0.97387214549729639, -0.15799427009588896, -0.27880422089608586, 0.028697166773400746, 0.65598146049505734, -1.4032934691064998, -0.27694791959460091, -0.93696934276576749, -0.34503187642813293, -1.2774302374771724, 0.35254215317590548, -2.0059066388508895, -0.54501479471571301, 0.56390744469313958, 0.34342867272292704, -0.039266111030168575, -0.46771796660612919, -0.5113379439803537, -0.67460924961212487, -1.4087075247325604, 0.76682621261655792, -1.4997631674363823, -0.61243627910077725, -1.140412010455059, 0.92607047340143789, 0.031738662464902812, -0.19464166358716931, -0.019574658382761297, 0.5907343301221667, 0.67219654831681863, 0.63526014786872564, 0.64691439703837572, 0.46755765237782537, 0.266047284332456, 1.5639259433368171, -0.1232842105363971, -0.79720843551321297, -1.3425220733405558, 0.10102791547609793, -1.2511621961709509, -1.1547569792642103, 0.90804259525693232, 0.55567477585800451, -0.69630039376833142, 1.8263285995817111, -1.1045860116363533, -1.1458232936355695, -0.24872102316672945, 0.87564297179583939, 0.34870630033170236, -0.11486532945911218, 0.8601445367496513, 0.44005667305299212, 1.2835109638424185, -1.3782866765007631, -0.50991879410031327, -0.068571767358020008, 0.55215258554278623, -0.1305387145071539, -0.78085884047607246, -0.49862379226704828, -1.0719226951252603, -3.9597843087634375, -1.7057486183894146, 0.58824753377686345, 0.037538948313628279, -0.31142059403406569, -0.9480099955663156, -0.87515503281571616, -0.22834742947928907, 0.32248540217529065, 0.14406535853452948, 0.19620781879501636, 1.4953297525593066, 0.57290182270256063, 0.83579489987201039, -1.7967656482657317, 0.15682319816807769, -0.91580478059805526, 0.76462319312972327, -2.4906624998259619, -0.55590609385845036, 0.23425682810465928, 1.3883711724071401, -0.012914546225988095, 0.2066156244499508, -1.4125191472494469, 0.46804377227475807, 2.6609157201939899, -2.6403914041405874, -0.55390426704981188, 0.23885890018691824, -0.2818318583278035, 0.093559704390950307, 0.70595440842491852, 1.0452412767927779, -0.77304155861740731, -1.2254542349282889, 1.2978873432669082, -0.59556260505888436, -0.99956089082803234, -0.40990460676161405, 1.0694625230993884, -0.39473191853023293, -0.23961021060563101, 0.88751797121745213, -0.21861562319399236, -1.5945098585081317, -0.93505992208397593, 0.76481223504234308, 0.40205618771362855, -0.34438631692070421, -0.93920569364152029, 0.19954015080464771, 0.3364185550662856, 0.75683003070854749, -0.51853460681612507, 0.22738658943064433, 0.20355985950906522, -0.3013658122597162, 0.59001201638395107, -0.265161135081731, -0.10880384119557773, -1.7399600154991111, 0.18493616197453516, 0.052572660499208418, 2.1877993401471301, -0.82403764602216489, 0.21839362508360241, -2.0600853727560064, -0.65348594883228406, -0.61286346765384503, -0.68115063057036751, 1.0242546785477791, -0.12350358640833176, 0.029627531322016426, -0.083097893296584374, 0.83434792744451647, -1.1730892018547028, 0.80868592435238262, -1.0285438374797979, 0.46945277518598261, -1.1624323819855371, 0.050935295497133076, 0.10596762041131924, -1.3615603986236544, 0.29502771863146482, 1.8508680675862796, -0.28094582239555543, 0.60401333700812243, 0.56727245317430763, 0.41952536801870605, -1.8938950456298789, 0.6515895940100167, -0.86679887558340385, -1.0130903757938499, -0.49529158925562755, 0.031629288481219812, -1.3211655138458465, 0.53084963592167866, -0.39338113966179827, -0.77633927961347071, -0.44320138309355872, 0.53080327502577052, 0.48602373626252865, -0.54098265778166899, 0.91285943332508679, 0.27908164450743511, -0.044341406387395962, -1.4836346881134332, 0.03584708477831472, 1.8223236090850643, 1.1908854755264193, 0.024042620913449539, 0.24167397740450455, -1.7599355634938088, -0.59099805226540481, -1.5797435344953654, 0.72111952422950021, 0.42770816698172265, -0.19806919899379993, 0.43097202951658437, -1.1354284736475861, -0.094771449697213933, 0.21448701788753374, -0.62935231505311617, 0.28396609250664817, -0.83502341591416862, -1.2549798379185841, 0.5659726610434449, -0.70104580984557519, -0.41619216360570077, -2.3381565463578711, -2.2642524912650264, -0.53523197889518848, 0.060013367054585119, 0.98360191177485035, 0.57688905656471223, -1.0180356375546633, 0.4203035802297308, -1.0338868843248468, -1.2073359473162546, 1.4500641574374591, -1.1057185423502562, 0.95829064911377781, 1.4016308360960521, -0.16628603127995448, -0.098873979438639722, -1.1395224856373789, 2.1371981486557066, 0.92972194250552986, 2.062545246110532, 1.5711894153756709, -1.7073815814644457, 0.62216343748530478, -0.75897320237711763, -0.23783014408735542, 2.1534863683708418, -0.49681169561136684, -0.29367696998086124, 0.44274192774518711, -0.24396454027550193, -0.26124200427595318, 0.74602581099195353, 1.0529808732523671, -1.4853106064384882, -1.6512138502385609, -0.73204421780661932, 1.4019530790987449, 1.6999112654664987, 1.1105882077160345, -0.0900092606863723, -0.22218887358597622, 0.95052041810916299, 0.13759220917488099, -0.73705799453618626, 0.83898246387840891, -0.70596569783998442, 1.8492965496495799, -0.10202771834027505, 0.027370306639225076, -0.41505133017486501, 0.55400370067339166, 1.3642049991796799, -2.1884814416795222, -0.20978829890110715, -1.2215888562424058, 0.45405978841720818, -0.021621613486579046, -1.4970367621648906, 1.3396661552744862, 1.0789269609384358, 0.35314664182162447, 0.57514995861551643, -0.52317815453808936, 0.81602149726383988, -1.5319270912629732, -0.32883524972803518, 0.46704509055139509, -0.092989556599845619, 1.6043448859982139, -0.54987705658046515, 1.0617278269201273, 0.20208262844966693, 1.1480824073238198, 0.97610202199848761, -0.84431938648208238, -2.360674839903993, -1.0884767891253539, -1.2992794601010778, -0.41553994736297128, 0.3939887087203095, 1.0415308004595036, 0.15734117311885881, -1.2925309397457414, 0.9101375707578101, -0.27109608179890354, 0.17590025337216336, -1.3745207792704066, -0.74963373874535344, -0.36315517627396432, -1.7806038594508038, 0.15113832439469427, -0.59075663053153538, 0.48652695631693027, -0.047583845499635215, 0.56194401822005091, 0.68048995109395682, -0.98327198916566372, -0.39922507200724722, -0.85769116997827266, -1.0443912053173829, 0.43352746263124503, -1.2518945838321247, 1.1324745176275697, -1.9497731091208095, 0.12961960166380215, -0.0185820567986127, -0.33503072561541319, 1.4099099693493227, 0.030820577025597089, 0.82438828578049217, -0.27531740056269138, 0.13187243335966883, -0.14026711563211497, -0.018036851075299551, 0.38660202375376468, 0.44535020972179834, -2.0020612823198976, 0.79779429807117996, -2.0407783511238802, 1.0027476607990229, 0.048683664895399423, 0.74212976061435032, 1.2158160124369761, 1.4546891206752597, 0.75108738714189172, 1.3325140260707451, -0.65403635863154352, -0.26666516900425513, 1.4885106429269332, 2.5783683490387439, -0.51639660330025194, -0.3519560196677628, -1.1141473669939317, 1.6058922869891459, 0.37476005514385619, -0.13219031222892327, 0.72733370451544088, -0.1626391169334738, -0.85695342848612566, -0.69421526613607665, -1.8134466383280445, 0.14735210356477443, 0.0098134680650266235, -0.15435674815275055, -2.4614875184020573, -1.3444130172115898, 1.1138429016479308, -0.73721060120168092, -1.7295431978328919, -0.42851342335838688, 0.39255592619369184, 1.1961033173366558, 0.62538218217422847, 2.2619128691504544, 0.066663632831568301, -0.74159698934405471, -0.84050630732946552, -0.53898371045929194, -1.250817909101237, 1.0868612382202774, -0.77419257550815257, 1.8756729751092851, -1.585175753800425, 1.1830965103345559, 0.57633992943278023, -1.6217669052433696, -0.85761384428328558, 0.27230972309344659, 0.68846094251477041, 1.3519503463946663, -0.37996511479326639, -0.26539876995189449, -2.4437823478300156, -0.79558478269483068, -0.5183532532673224, -1.207282452799435, -0.17796548915041646, -0.0011757829601953421, 0.5099152200941478, 0.21842859202765808, 1.4232573962610322, -0.51571481797414087, -0.058658856869761015, 0.62541499379062937, 1.2477602765628075, 0.64865809572171185, 1.1815794794031615, -0.096712100852888644, -0.47343187791820063, 1.1642637521346422, -0.31849676581647429, -0.59518777855214544, -0.13572129819671483, 1.3879838973507728, 1.9261310775139338, -1.420433375501974, -1.3320132605604673, 0.040432388279802334, -0.85823962854894231, -1.2064764866304605, -0.21354935781098963, -2.1788844467107249, 1.3105053601941712, -0.91265154421471617, -0.87308243503740368, 0.090513683661449282, 0.21211865625265841, 0.1974467217986062, 1.0937236203475169, 1.1307184832900867, -0.38728095532341061, 0.23004596994421603, 0.48350694019133544, 0.011959177758937437, -1.2331625720145625, -0.081944556191949181, 0.8457529868497049, -0.35544947088577267, 0.85007692658451939, -0.60207064330247539, -0.47309727651890693, -0.66512634805875626, 0.11370451171083809, -0.16947233562938605, -1.7067357130054011, 1.688574101224674, 0.49723464225016772, -0.43327828447548627, 0.71874161662031166, 0.80567496754018575, 1.3959999489377315, 1.3215695942468131, -0.2944311779672632, -1.1067579595785015, -0.082300280525305372, -0.27416412062782508, -0.76201563737143962, -0.9210127936773489, 0.41233109763645881, -0.42630616789387021, 0.44027878513568697, 0.36112130465521181, -0.95901307262311342, 0.60768555203235453, -1.5757638131750336, 0.4096426299847909, 0.21195141882533322, -0.85303928231031223, 0.77575193298558287, 0.66249430125856523, 1.8759772987072312, 0.62293504307047198, 1.2480524844683012, 0.00064150826904312193, -1.0156995556390414, -1.5250485995399292, -0.69460384536932296, 1.28362824789898, 1.482518052447598, 0.97469348308739867, 1.113320786325291, 1.0170039609649062, -1.3889279551597706, -0.64205430494916771, -0.52099002038734876, -0.33343136037310667, 0.33409669816300935, 1.3196970873021228, 0.38596317160271715, -0.31999703848290662, 0.81425336280324734, -0.73696444646209369, -0.97448507193218736, -0.98195981179013159, 0.094767622862372322, 1.3909552475630753, 1.2180369609835258, 0.74011770092461959, -0.91869751713856374, -0.79496300886777294, -0.014483039910042962, -1.7240702637000831, 1.0467895234540701, 1.5928613297280949, 0.50716637550895272, -0.70747181739646159, -0.13860188972085583, -1.0344982058008689, -0.74458697638255933, 0.4820324251768755, -0.50141201741546293, -0.29843407337292976, -0.49150873502715198, -0.69278430936346824, 1.7659373011851778, 0.005205747085697255, -0.37202550827287773, 0.56933172776676066, 1.1510602662229232, -0.0022872898010393499, 0.67615188792203929, 1.0366141191442644, 0.21202753906725427, 0.7931325434451475, 0.63725133247181398, 0.76229604392847505, -0.31552782582331218, -2.0915372050758561, 0.16544601437699749, -0.84583552583399535, 0.76383846876691019, 0.21820987096094277, -0.78518586192770357, -0.84025960778351527, -1.5325514625620356, 0.30690827581018448, -1.7195638681258498, 0.84714947156949405, -1.1206796924059939, 1.5736643162976676, -1.5556777053476101, 0.43092877058870804, -0.04513090978693645, -0.27877018777096579, -0.44868597051051784, 0.60556101824305242, 0.83142556218110164, 0.42207924745553332, 1.7941979822224374, 1.3332823389470836, 0.62616059963313109, -1.2839919268927475, -0.60993463131784353, -0.043188054926870528, 0.18334932409739707, 0.39196090717168391, -0.36366864820663669, 0.13124744357284535, 1.0435327292110967, 1.2466405507440141, -0.59702574382042284, -0.59523965530368772, 0.28646356847474486, -0.56602877644704486, -0.35686342562532408, 1.1922317983885706, 1.8022444264421926, 0.58886651103587195, -0.19817796687047193, -0.080281709885447833, -1.3197343943567768, 0.56116545400961881, 0.48315797295505519, -0.070470947953476901, -0.066839042900311646, 1.9271414868100891, 0.091981266231645362, 0.080427107045483906, 3.4387760642218459, 0.74328490913077971, -0.0011331604292491653, 1.5434210905854084, 0.46970890995705161, -0.29090708578940849, -2.1750810924305362, -1.3274608938300749, 1.19212392525722, 0.17540000580029858, 0.4476129102572502, 0.79539575077639013, -0.60630861086905419, 0.78112936385366627, -0.27039132754484629, 0.12869316512425594, -0.50364142583551841, 1.5312270407362245, 0.096406379964907141, -0.065154847286283249, -0.86168901510995921, -0.41586552933500393, 0.39966809627084204, 1.9849590893949294, -0.24967124948588254, 0.64255541933008631, -0.13341194308556076, -0.027179348213425134, -0.73379607623669529, -0.92554886819472904, -1.6239042580567822, 0.037167106480414824, 0.88778398256701041, -1.0719170162215992, 0.26018921841800896, 0.74120410713320861, 1.1867120364216903, 0.19310056861906852, -0.32081931806399666, 0.62128301014523113, -0.85929208152396019, 0.036685491942098719, 0.83761593282608093, 0.29268750077689326, 1.9845901545714724, 0.38820661329436562, -0.33644356053324176, 1.5982808742112249, 1.5848860073457134, 0.96790090037811105, 0.62079119732681276, -0.84088053433624022, 1.2112818023984919, 0.5171137806605427, 1.1521155819107323, -0.6201619413135373, -1.2750153323351852, 1.0251436866172421, -0.61711258858064755, -0.56750277235712365, 1.9598850111138499, 0.39795839989079612, 0.31949282605999041, -0.78992450142629589, 0.25791715475354898, -0.67955282357171609]</Parameters>
			</FullConnection>
			<FullConnection class="pybrain.structure.connections.full.FullConnection" name="FullConnection-14">
				<inmod val="SigmoidLayer-8"/>
				<outmod val="SigmoidLayer-17"/>
				<Parameters>[-0.0096144828778221177, -0.96683804470082335, -0.29928158451947096, -0.64933379015892867, -1.157148726644508, 0.35745020881340184, 1.6420690378321168, -0.48049382870464008, -0.89669000892585138, 0.15418213777028117, 0.54929311904486533, 1.2386436851846419, -1.9667109266688503, 0.94060654912587394, 0.55001838456068186, -1.3697988869431257, -0.058973141191916795, -0.94327460278945829, -0.88402674789051905, -0.9080578591782571, -0.91762268861603791, -1.0114775250144714, 0.20703968067172118, -1.3997986348553211, 1.4889713492059322, -1.0211265593597909, 1.7545753420232713, 0.64988409641290357, 1.7403299960470908, -1.0023453138810021, -1.2671088993292237, 1.4119503390874659, -0.38599108117436409, 0.0021667997674686547, -1.5412996764345321, 0.15471827249414602, -0.25386694825191874, -1.3720264390084684, 0.36386362173325615, 0.35127103229870937, -1.1340569919839805, 0.7041746419747642, 1.9656751568044366, -0.40569410787703231, 1.124233653888504, 0.70435702326300531, 0.52846592851264063, -0.54062778107719478, 0.70203515116829529, 1.7055818313729074, -0.52995474864232095, 1.6961490212412516, -0.24144686459225378, 1.1335068422821619, 0.18686887439749078, 0.048201954440502216, 0.071869421511092768, -0.59635844120590187, -0.68054816500866766, -1.0014033427274085, -1.3611750866014356, -1.6770044642039315, 0.046968791618526712, 0.30237893594254261, -0.57797487618328625, -0.043395443330445316, 0.61304663928691572, 0.31650273870123324, 1.3218232805139634, -0.10329512106665585, 0.031031779420838713, -0.6038207608612165, 1.6122550604303347, 0.11636526518214516, -0.33885217233677056, -0.27014452850877746, -0.29534871738157964, 0.056134606510325716, 0.84861675861938801, 0.22385273487102067, 0.95195278502428249, -1.301695195059851, -0.51179037828415785, -0.73151163099759253, -0.34285310031104149, 0.73450167552348222, 1.2651161336493786, -0.79486176237003725, -0.73148546804312631, -0.44305898188952159, 0.17171874186909641, -1.6954257125964864, -1.7506241304637111, 0.010118094869234288, 0.19189830499176957, -0.77703679078856702, -1.0463969866692069, 0.2587355673793264, -0.18745618797101482, -1.038384228962991]</Parameters>
			</FullConnection>
			<FullConnection class="pybrain.structure.connections.full.FullConnection" name="FullConnection-13">
				<inmod val="SigmoidLayer-17"/>
				<outmod val="SigmoidLayer-18"/>
				<Parameters>[0.36906257892977995, -0.75099183606051401, 0.22316028780108463, -1.0120106874972343, 0.56028152701111622, 0.91535948835371406, -0.4307012372250783, -1.0385781543147088, -1.0288823457227187, 0.42606886886270567, -0.4782030990954767, -0.71390429553766088, -1.3777927159876358, 1.3513637231890094, 0.42355482780610687, -0.54057891927112744, -1.2310791011947402, 0.24113285141320367, -1.7353627905287818, 0.40503421445921928, -0.90645505208162591, 0.76812468026584335, -0.94982300256492413, -0.90362835690819765, -0.051016419250250335, -1.6523252980257872, -1.25297292814161, 0.13802790106877577, 2.5670251122507994, -1.3613037992002468, -0.13497257672275209, 0.23638084824386879, -0.99174277502616204, -0.2550307820215425, -0.17271313884472164, -1.5364824585389225, -0.92939453495331414, -1.2094986549733504, -0.30442343030336905, -0.63077467433267864, 0.90840782549188326, -0.44465807632011228, -0.22099406075385811, -0.51453994774751155, -0.75494989961009773, -1.4409705698816004, 0.0065283504806068673, -0.4367518080973119, 1.4840888603291353, 0.0098008355815795336, -1.6888376514188752, 0.48776694628274742, 0.13855510583485192, -0.12907236827997104, -1.9536516271186999, 0.61325341819992063, -1.2180934687357643, -1.5074958737142483, -0.37195226204263243, -0.74312958483879721, 0.86569403115461641, 0.16909310931051558, -0.33231646102810752, 0.49562497619131768, -1.808413409871594, -0.48762611665590938, 0.26344798910095935, -1.2875331647644785, -0.84539139895693927, -0.4594528432995183, -0.55003284648453621, -0.37286950668667784, 0.29732476920767809, -0.49054016058192162, 1.2702065881484894, -1.0396074245042166, 0.6450604240776342, 0.4341694637706579, -0.8718709364399152, 0.7888646619269637, -0.06464873348348886, 0.60741824692375246, 0.9486594514203287, 0.18636090777766953, -2.0265704149884458, -1.0527157607921769, -0.20158735951224249, -1.2742468124636084, 0.70374939859368268, -0.1229287272685857, 0.57450286083756552, 1.974810997563295, 0.31783805867818843, -0.17363146795091913, -0.826546293934871, -1.5601857548356417, 0.63520663262391153, -1.4739343981014099, -0.05414395251813181, 0.12983017426979784]</Parameters>
			</FullConnection>
			<FullConnection class="pybrain.structure.connections.full.FullConnection" name="FullConnection-12">
				<inmod val="SigmoidLayer-18"/>
				<outmod val="SigmoidLayer-19"/>
				<Parameters>[-0.33541437346943492, 1.6023045170696009, 0.90820984483300549, -0.3850380747717016, -0.67835957121227664, -1.3259945558890849, -0.83337874893536135, 0.58881274501567227, -0.83175625708202683, -0.87832945802149875, -0.52939001675249486, -0.088598862793817804, 2.2842705825127152, 0.96380821884065915, 1.2845057299795737, 0.66043772770407061, 0.48655167851039693, 0.3521498684398347, -0.21754464670386053, 0.96606615048071265, -0.54738016608938689, -0.038951830352246933, 0.075597556202876254, 0.5374019332507417, -0.36675014387065202, 0.1905846487405822, 0.019569782016601391, -0.72158742398777187, 2.3589844336246468, -1.3988298289228058, -0.71940126062453702, -0.42913283123508045, -0.17539417358923809, 1.5823419617466497, 0.13506419273401232, -2.540316373316633, -0.01295097412829682, -1.1255118288347914, 0.54684505638819714, 0.19099471505674825, 0.71144580038583582, 1.6296070971558905, 2.5094926857371336, 2.4136134621074037, 0.86349270331859707, 0.62779042024878495, -0.39707254986809731, -0.1182061347425775, 2.2803419913231804, 1.6475940520840846, 0.19083199075895838, 0.46298111321363838, 0.18921134634182471, -1.0292834439439722, 0.35616992238645973, -0.64569820978935377, -1.4892957587014319, 0.10114086052082594, 0.8971916704662557, -0.17509887468553922, 0.46232828676352267, 0.13291074497885627, 1.1197908989019068, 0.021567191186159875, 0.62782565429459858, -0.96285276710684098, 0.22479813998408749, 0.90890948117221471, -1.3791938460345481, 0.66189710452677797, 2.8924207092494068, 1.3721428922827041, 1.7643800169403665, -0.61931612964155913, 1.5250421617792524, -0.32892107703407375, -0.64117103908926909, 3.8849559658736865, 0.14443956642033998, 0.60143560835817167, -0.36236751663038674, -0.53883129713729294, 0.12661304337156021, -0.59639144806212563, -0.61565854257363406, -0.55863259777654917, -1.3933472654464045, 0.26128972014864632, -1.5961524857196077, 1.1440378749961189, -0.12762012288072366, 1.2726923167762416, 1.0873677291808166, 0.88138473268224315, -0.75431561328452945, -0.53009248178285417, 0.074936042523290433, -1.1320712748909552, -0.6749882326123714, 0.91474664993652111]</Parameters>
			</FullConnection>
			<FullConnection class="pybrain.structure.connections.full.FullConnection" name="FullConnection-11">
				<inmod val="SigmoidLayer-19"/>
				<outmod val="SigmoidLayer-20"/>
				<Parameters>[-0.82621826695392886, -2.6312107932843953, -1.1256084048019108, 4.3760022361768449, -2.0091801512108836, -1.8264250897333909, -0.32147791910599166, 4.4146734015562084, -1.2763554218940438, 0.92485313856011375, 0.98031878114644588, 0.60013808084250619, 1.521679115886063, 1.2625661981030085, 0.77886081744540037, 0.32844802698055225, 0.78771805346473023, -0.44848325629407848, 0.29622971391488434, 1.078872216856636, -1.8949427207683187, -1.9180962076982526, 4.1925966559084351, 0.46322484181572376, 0.30249400305930219, -2.883549360225178, 1.1816717939180332, 0.93270491955440882, -0.49509694110746882, -1.4902010279142168, 2.0796349205176674, -0.39471039370125033, 0.16009030831674864, -1.4748188345698159, -0.066860021630576041, 0.8442664046999302, 0.22622653892404204, -0.86924855089466491, 0.6671864865835051, -2.6146169414624856, -0.93166875311015251, -2.0541092392007085, -0.88155646600770254, 1.2098938343980425, -0.47141097587225311, 1.7283406244550572, 0.50762711715602837, -1.5173342517400392, 1.4784983791142521, -1.2759440696954683, 0.24520044419417342, 0.043275018574228524, 1.1668781223987805, 0.070361704881840015, -0.82983726984792561, -2.2049364249105525, 1.2302929102822493, -3.2855651100236662, 1.1352623290029895, -0.74288281792317024, -2.6836260529498603, 3.684850783484833, -1.1807321235163519, -1.2352049189309824, 1.2450815019961727, 5.1225640267481518, -4.1194433394751613, -2.1844138577350218, -1.7080432959611693, 0.9674912161069037, 3.3026019026822575, -0.84744959725891966, -1.3048690555825864, 6.6754780810635834, -1.9708517778098493, 0.79107350465237691, -0.092684650813789057, 1.3138234895673211, -2.2201491309643626, -2.1089814329673713, 0.12469256477130114, -0.82487872163026932, -0.74719377455373637, 0.46836539913127323, -0.6056084416886498, 0.067402854059422118, -1.4023043949880587, 0.37284793454376314, 0.42131094669418861, -1.3851319714606294, -1.1690970676231922, 1.0402525370540598, -0.54848542453848603, 1.8296105504783835, 0.86079384947321069, -0.42026410913069212, 2.4706164466852036, 1.8035685706715963, 1.9327891212453785, 1.4234547392869163]</Parameters>
			</FullConnection>
			<FullConnection class="pybrain.structure.connections.full.FullConnection" name="FullConnection-9">
				<inmod val="SigmoidLayer-20"/>
				<outmod val="SoftmaxLayer-16"/>
				<Parameters>[-1.311677870558156, -0.095269486244970891, -3.2886662194458331, 0.73931503380270303, 0.45582333582159718, -1.692300411392583, 6.3388470636889327, -0.5608345503466694, 0.66428704024663576, 0.11545621470681385, -2.0811946762091291, 2.172424144002941, 1.8021899879935142, 0.50217866094825536, -0.95424298023097298, 2.496376270969388, -0.6959884325569623, -5.3044405852212506, -0.50180772743192747, 1.0317450610562395, 5.0894584546320338, -2.8433350454868518, 1.9206635498374158, -2.8838692689118854, -0.021413687082297839, -1.2840111969615484, -6.3432578988700019, 3.4860213050794355, 0.94807269026016838, -3.3380363185186677]</Parameters>
			</FullConnection>
		</Connections>
	</Network>
</PyBrain>
